napari_epyseg/__init__.py
napari_epyseg/napari.yaml
napari_epyseg/start_epyseg.py
napari_epyseg-0.0.10.dist-info/licenses/LICENSE
napari_epyseg-0.0.10.dist-info/METADATA
napari_epyseg-0.0.10.dist-info/WHEEL
napari_epyseg-0.0.10.dist-info/entry_points.txt
napari_epyseg-0.0.10.dist-info/top_level.txt
napari_epyseg-0.0.10.dist-info/RECORD
