Metadata-Version: 2.4
Name: napari-epyseg
Version: 0.0.10
Summary: Napari plugin to segment epithelia with EpySeg
Home-page: https://github.com/Image-Analysis-Hub/napari-epyseg
Author: Gaëlle Letort
License: BSD-3-Clause
Project-URL: Bug Tracker, https://github.com/Image-Analysis-Hub/napari-epyseg/issues
Project-URL: Documentation, https://github.com/Image-Analysis-Hub/napari-epyseg#README.md
Project-URL: Source Code, https://github.com/Image-Analysis-Hub/napari-epyseg
Project-URL: User Support, https://github.com/Image-Analysis-Hib/napari-epyseg/issues
Classifier: Development Status :: 2 - Pre-Alpha
Classifier: Framework :: napari
Classifier: Intended Audience :: Developers
Classifier: License :: OSI Approved :: BSD License
Classifier: Operating System :: OS Independent
Classifier: Programming Language :: Python
Classifier: Programming Language :: Python :: 3
Classifier: Programming Language :: Python :: 3 :: Only
Classifier: Programming Language :: Python :: 3.8
Classifier: Programming Language :: Python :: 3.9
Classifier: Programming Language :: Python :: 3.10
Classifier: Topic :: Scientific/Engineering :: Image Processing
Requires-Python: <3.11
License-File: LICENSE
Requires-Dist: epyseg
Requires-Dist: napari<=0.6.5
Requires-Dist: numpy
Requires-Dist: magicgui
Requires-Dist: tifffile<=2024.12.12
Requires-Dist: pillow
Provides-Extra: testing
Requires-Dist: tox; extra == "testing"
Requires-Dist: pytest; extra == "testing"
Requires-Dist: pytest-cov; extra == "testing"
Requires-Dist: pytest-qt; extra == "testing"
Requires-Dist: napari; extra == "testing"
Requires-Dist: pyqt5; extra == "testing"
Dynamic: license-file
